{
  "tasks": [
    {
      "id": 7,
      "content": "A Teste",
      "categoria": "Categoria teste 7",
      "categoriaId": 7
    },
    {
      "id": 8,
      "content": "B Teste",
      "categoria": "Categoria teste 8",
      "categoriaId": 8
    },
    {
      "id": 9,
      "content": "C Teste",
      "categoria": "Categoria teste 9",
      "categoriaId": 9
    },
    {
      "id": 10,
      "content": "B Teste",
      "categoria": "Categoria teste 10",
      "categoriaId": 10
    },
    {
      "id": 11,
      "content": "A Teste",
      "categoria": "Categoria teste 11",
      "categoriaId": 11
    },
    {
      "id": 15,
      "content": "B Teste",
      "categoria": "Categoria teste 15",
      "categoriaId": 15
    },
    {
      "id": 16,
      "content": "Legal",
      "categoriaId": "150",
      "categoria": "Categoria 1"
    },
    {
      "id": 17,
      "content": "Teste Testinho",
      "categoriaId": "15666",
      "categoria": "Categoria 3"
    }
  ]
}